Metadata-Version: 2.1
Name: pciids-ilker-manap
Version: 0.0.1
Summary: classes for pciid database
Home-page: https://github.com/ilkermanap/python-pciids
Author: Ilker Manap
Author-email: ilkermanap@gmail.com
License: UNKNOWN
Platform: UNKNOWN
Classifier: Programming Language :: Python :: 3
Classifier: License :: OSI Approved :: MIT License
Requires-Python: >=3.6
